{"cacheVersion":39,"page":{"id":"766b2683-f0dd-4072-be42-f4882aff3f4d","paths":{"en":"child-safety","default":"child-safety"},"cmsDataSetPath":null,"workflows":[]},"sections":{"270cb110-34fe-4488-8a3b-f02752114f81":{"uid":"270cb110-34fe-4488-8a3b-f02752114f81","linkId":"c6c5d73c-c10c-4403-bb2d-0a17f40f9a5f","_state":{"style":{"default":{"width":"100%","display":"flex","padding":"80px 0","backgroundColor":"#F9F7FF"}},"states":[],"interactions":[]},"content":{"default":{"wwObjects":[{"uid":"4635a1bd-dd52-43a8-8d74-f231ecd45510","isWwObject":true}],"_ww-layout_alignItems":"center","_ww-layout_justifyContent":"center"}},"sectionBaseId":"99586bd3-2b15-4d6b-a025-6a50d07ca845","sectionTitle":"Hero Section"},"42fb6812-db55-4f2e-8698-30ca47a74299":{"uid":"42fb6812-db55-4f2e-8698-30ca47a74299","linkId":"65e5b368-d0dc-4600-ae2c-ad31416b208c","_state":{"style":{"default":{"width":"100%","display":"flex","padding":"80px 0","backgroundColor":"#FFFFFF"}},"states":[],"interactions":[]},"content":{"default":{"wwObjects":[{"uid":"3d090f1d-7a6a-413e-a3d9-b1ddd7ca74c3","isWwObject":true}],"_ww-layout_alignItems":"center","_ww-layout_justifyContent":"center"}},"sectionBaseId":"99586bd3-2b15-4d6b-a025-6a50d07ca845","sectionTitle":"Our Commitment Section"},"97107eea-e44c-4ef1-bd14-a652493f6c8d":{"uid":"97107eea-e44c-4ef1-bd14-a652493f6c8d","linkId":"588146b2-a248-4e32-8137-7e06b8eab8ad","_state":{"style":{"default":{"top":"0px","left":"0px","width":"100%","zIndex":"100","display":"flex","padding":"16px 24px","position":"fixed","boxShadow":"0px 4px 10px rgba(0,0,0,0.05)","backgroundColor":"#FFFFFF"}},"states":[],"interactions":[]},"content":{"default":{"wwObjects":[{"uid":"6b58f8b6-4044-4f60-8257-f6982206e753","isWwObject":true},{"uid":"6d5f33a8-075f-434d-8d4a-4a3a2d2e4d4d","isWwObject":true}],"_ww-layout_alignItems":"center","_ww-layout_flexDirection":"row","_ww-layout_justifyContent":"space-between"}},"sectionBaseId":"99586bd3-2b15-4d6b-a025-6a50d07ca845","sectionTitle":"Navbar Section"}},"wwObjects":{"3f6f4d21-f455-441d-8a87-f453689c90d7":{"uid":"3f6f4d21-f455-441d-8a87-f453689c90d7","_state":{"style":{"default":{"margin":"0 0 24px 0"}},"states":[],"interactions":[]},"content":{"default":{"tag":"h1","text":{"en":"Child Safety Standards"},"_ww-text_text":{"en":"Child Safety Standards"},"_ww-text_color":"#61378D","_ww-text_fontSize":"48px","_ww-text_fontWeight":"700","_ww-text_lineHeight":"1.2"}},"name":"Hero Title","wwObjectBaseId":"d7904e9d-fc9a-4d80-9e32-728e097879ad","libraryComponentBaseId":null,"parentSectionId":"270cb110-34fe-4488-8a3b-f02752114f81"},"4635a1bd-dd52-43a8-8d74-f231ecd45510":{"uid":"4635a1bd-dd52-43a8-8d74-f231ecd45510","_state":{"style":{"default":{"width":"100%","display":"flex","padding":"0 32px","maxWidth":"1200px","textAlign":"center"}},"states":[],"interactions":[]},"content":{"default":{"children":[{"uid":"3f6f4d21-f455-441d-8a87-f453689c90d7","isWwObject":true},{"uid":"e00eeec5-6c90-445a-b245-3e351b13e0a5","isWwObject":true},{"uid":"9229b7ff-3d1d-4f10-83d1-8a949ca4d150","isWwObject":true}],"_ww-text_text":{"en":""},"_ww-text_textAlign":"center","_ww-layout_alignItems":"center","_ww-layout_flexDirection":"column"}},"name":"Hero Container","wwObjectBaseId":"b783dc65-d528-4f74-8c14-e27c934c39b1","libraryComponentBaseId":null,"parentSectionId":"270cb110-34fe-4488-8a3b-f02752114f81"},"e00eeec5-6c90-445a-b245-3e351b13e0a5":{"uid":"e00eeec5-6c90-445a-b245-3e351b13e0a5","_state":{"style":{"default":{"margin":"0 0 32px 0","maxWidth":"800px"}},"states":[],"interactions":[]},"content":{"default":{"tag":"p","text":{"en":"Animal Mitra is committed to protecting children and fostering a safe community. We strictly prohibit CSAM (child sexual abuse material) and sexual exploitation or endangerment of minors. This page explains our standards, reporting process, and designated safety contact."},"_ww-text_text":{"en":"Animal Mitra is committed to protecting children and fostering a safe community. We strictly prohibit CSAM (child sexual abuse material) and sexual exploitation or endangerment of minors. This page explains our standards, reporting process, and designated safety contact."},"_ww-text_color":"#333333","_ww-text_fontSize":"18px","_ww-text_lineHeight":"1.6"}},"name":"Hero Description","wwObjectBaseId":"d7904e9d-fc9a-4d80-9e32-728e097879ad","libraryComponentBaseId":null,"parentSectionId":"270cb110-34fe-4488-8a3b-f02752114f81"},"9229b7ff-3d1d-4f10-83d1-8a949ca4d150":{"uid":"9229b7ff-3d1d-4f10-83d1-8a949ca4d150","_state":{"style":{"mobile":{"display":"flex"},"default":{"display":"flex"}},"states":[],"interactions":[]},"content":{"mobile":{"_ww-layout_flexDirection":"column"},"default":{"children":[{"uid":"f8bec16e-8c30-4a2a-9769-4da84b54c585","isWwObject":true},{"uid":"2ed0f45c-338b-4915-ac78-9a74f75d94dc","isWwObject":true}],"_ww-layout_rowGap":"16px","_ww-layout_columnGap":"16px","_ww-layout_alignItems":"center","_ww-layout_flexDirection":"row"}},"name":"Hero Buttons","wwObjectBaseId":"b783dc65-d528-4f74-8c14-e27c934c39b1","libraryComponentBaseId":null,"parentSectionId":"270cb110-34fe-4488-8a3b-f02752114f81"},"f8bec16e-8c30-4a2a-9769-4da84b54c585":{"uid":"f8bec16e-8c30-4a2a-9769-4da84b54c585","_state":{"link":{"href":"safety@animalmitra.com?subject=Urgent Safety Report – Animal Mitra","type":"mail"},"style":{"mobile":{},"default":{"cursor":"pointer","padding":"16px 32px","transition":"all 0.2s ease","borderRadius":"8px","backgroundColor":"#FF6E06"},"_wwHover_default":{"backgroundColor":"#E05D00"}},"states":[{"id":"_wwHover","label":"hover"}],"interactions":[]},"content":{"mobile":{},"default":{"text":{"en":"Report a Concern"},"disabled":false,"buttonType":"button","_ww-text_text":{"en":"Report a Concern"},"_ww-text_color":"#FFFFFF","_ww-text_fontSize":"16px","_ww-text_fontWeight":"600"},"_wwHover_default":{}},"name":"Report a Concern Button","wwObjectBaseId":"59dca300-db78-42e4-a7a6-0cbf22d3cc82","libraryComponentBaseId":null,"parentSectionId":"270cb110-34fe-4488-8a3b-f02752114f81"},"2ed0f45c-338b-4915-ac78-9a74f75d94dc":{"uid":"2ed0f45c-338b-4915-ac78-9a74f75d94dc","_state":{"link":{"href":"safety@animalmitra.com","type":"mail"},"style":{"mobile":{},"default":{"border":"2px solid #61378D","cursor":"pointer","padding":"16px 32px","transition":"all 0.2s ease","borderRadius":"8px","backgroundColor":"transparent"},"_wwHover_default":{"backgroundColor":"#61378D"}},"states":[{"id":"_wwHover","label":"hover"}],"interactions":[]},"content":{"mobile":{},"default":{"text":{"en":"Email Safety Team"},"disabled":false,"buttonType":"button","_ww-text_text":{"en":"Email Safety Team"},"_ww-text_color":"#61378D","_ww-text_fontSize":"16px","_ww-text_fontWeight":"600"},"_wwHover_default":{"_ww-text_color":"#FFFFFF"}},"name":"Email Safety Team Link","wwObjectBaseId":"59dca300-db78-42e4-a7a6-0cbf22d3cc82","libraryComponentBaseId":null,"parentSectionId":"270cb110-34fe-4488-8a3b-f02752114f81"},"24679da8-507a-4947-b204-6ff4511aba16":{"uid":"24679da8-507a-4947-b204-6ff4511aba16","_state":{"style":{"default":{"margin":"0 0 48px 0"}},"states":[],"interactions":[]},"content":{"default":{"tag":"h2","text":{"en":"Our Commitment"},"_ww-text_text":{"en":"Our Commitment"},"_ww-text_color":"#61378D","_ww-text_fontSize":"36px","_ww-text_textAlign":"center","_ww-text_fontWeight":"700"}},"name":"Commitment Title","wwObjectBaseId":"d7904e9d-fc9a-4d80-9e32-728e097879ad","libraryComponentBaseId":null,"parentSectionId":"42fb6812-db55-4f2e-8698-30ca47a74299"},"3d090f1d-7a6a-413e-a3d9-b1ddd7ca74c3":{"uid":"3d090f1d-7a6a-413e-a3d9-b1ddd7ca74c3","_state":{"style":{"default":{"width":"100%","display":"flex","padding":"0 32px","maxWidth":"1200px"}},"states":[],"interactions":[]},"content":{"default":{"children":[{"uid":"24679da8-507a-4947-b204-6ff4511aba16","isWwObject":true},{"uid":"50331479-50ae-419f-a054-42fccec4101a","isWwObject":true}],"_ww-layout_flexDirection":"column"}},"name":"Commitment Container","wwObjectBaseId":"b783dc65-d528-4f74-8c14-e27c934c39b1","libraryComponentBaseId":null,"parentSectionId":"42fb6812-db55-4f2e-8698-30ca47a74299"},"ddf11cee-3ebf-4be6-b86a-d869e8119004":{"uid":"ddf11cee-3ebf-4be6-b86a-d869e8119004","_state":{"style":{"mobile":{},"default":{"width":"48px","height":"48px","margin":"0 0 16px 0"},"_wwHover_default":{}},"states":[],"interactions":[]},"content":{"mobile":{},"default":{"icon":"lucide/shield","color":"#61378D"},"_wwHover_default":{}},"name":"CSAM Icon","wwObjectBaseId":"1b1e2173-9b78-42cc-a8ee-a6167caea340","libraryComponentBaseId":null,"parentSectionId":"42fb6812-db55-4f2e-8698-30ca47a74299"},"bc80899b-5bd7-4eae-972a-267d526d1ca8":{"uid":"bc80899b-5bd7-4eae-972a-267d526d1ca8","_state":{"style":{"mobile":{},"default":{"margin":"0 0 16px 0"},"_wwHover_default":{}},"states":[],"interactions":[]},"content":{"mobile":{},"default":{"tag":"h3","text":{"en":"Zero Tolerance for CSAM"},"_ww-text_text":{"en":"Zero Tolerance for CSAM"},"_ww-text_color":"#61378D","_ww-text_fontSize":"24px","_ww-text_fontWeight":"600"},"_wwHover_default":{}},"name":"CSAM Title","wwObjectBaseId":"d7904e9d-fc9a-4d80-9e32-728e097879ad","libraryComponentBaseId":null,"parentSectionId":"42fb6812-db55-4f2e-8698-30ca47a74299"},"4cc4ac0c-6d5e-48ab-a636-9e32a7bd1694":{"uid":"4cc4ac0c-6d5e-48ab-a636-9e32a7bd1694","_state":{"style":{"mobile":{},"default":{"margin":"0"},"_wwHover_default":{}},"states":[],"interactions":[]},"content":{"mobile":{},"default":{"tag":"p","text":{"en":"We prohibit CSAM and any content that sexualizes minors. We promptly remove such content, ban involved accounts, preserve lawful evidence, and report to relevant authorities in accordance with applicable law."},"_ww-text_text":{"en":"We prohibit CSAM and any content that sexualizes minors. We promptly remove such content, ban involved accounts, preserve lawful evidence, and report to relevant authorities in accordance with applicable law."},"_ww-text_color":"#333333","_ww-text_fontSize":"16px","_ww-text_lineHeight":"1.6"},"_wwHover_default":{}},"name":"CSAM Description","wwObjectBaseId":"d7904e9d-fc9a-4d80-9e32-728e097879ad","libraryComponentBaseId":null,"parentSectionId":"42fb6812-db55-4f2e-8698-30ca47a74299"},"23a02d65-9652-41f6-acee-764583a38e85":{"uid":"23a02d65-9652-41f6-acee-764583a38e85","_state":{"style":{"mobile":{},"default":{"border":"1px solid #E5E7EB","display":"block","padding":"32px","boxShadow":"0 4px 6px rgba(0, 0, 0, 0.1)","transition":"all 0.2s ease","borderRadius":"12px","backgroundColor":"#FFFFFF"},"_wwHover_default":{"boxShadow":"0 8px 25px rgba(0, 0, 0, 0.15)"}},"states":[{"id":"_wwHover","label":"hover"}],"interactions":[]},"content":{"mobile":{},"default":{"children":[{"uid":"ddf11cee-3ebf-4be6-b86a-d869e8119004","isWwObject":true},{"uid":"bc80899b-5bd7-4eae-972a-267d526d1ca8","isWwObject":true},{"uid":"4cc4ac0c-6d5e-48ab-a636-9e32a7bd1694","isWwObject":true}]},"_wwHover_default":{}},"name":"CSAM Card","wwObjectBaseId":"b783dc65-d528-4f74-8c14-e27c934c39b1","libraryComponentBaseId":null,"parentSectionId":"42fb6812-db55-4f2e-8698-30ca47a74299"},"ce7a33b3-5025-4f76-8feb-1495196afda9":{"uid":"ce7a33b3-5025-4f76-8feb-1495196afda9","_state":{"style":{"mobile":{},"default":{"width":"48px","height":"48px","margin":"0 0 16px 0"},"_wwHover_default":{}},"states":[],"interactions":[]},"content":{"mobile":{},"default":{"icon":"lucide/shield","color":"#61378D"},"_wwHover_default":{}},"name":"Children Icon","wwObjectBaseId":"1b1e2173-9b78-42cc-a8ee-a6167caea340","libraryComponentBaseId":null,"parentSectionId":"42fb6812-db55-4f2e-8698-30ca47a74299"},"16148ed9-cf79-47b0-bb66-a95c7c715d03":{"uid":"16148ed9-cf79-47b0-bb66-a95c7c715d03","_state":{"style":{"mobile":{},"default":{"border":"1px solid #E5E7EB","display":"block","padding":"32px","boxShadow":"0 4px 6px rgba(0, 0, 0, 0.1)","transition":"all 0.2s ease","borderRadius":"12px","backgroundColor":"#FFFFFF"},"_wwHover_default":{"boxShadow":"0 8px 25px rgba(0, 0, 0, 0.15)"}},"states":[{"id":"_wwHover","label":"hover"}],"interactions":[]},"content":{"mobile":{},"default":{"children":[{"uid":"ce7a33b3-5025-4f76-8feb-1495196afda9","isWwObject":true},{"uid":"fbeff0a3-03b0-4a10-8155-e2ac14045433","isWwObject":true},{"uid":"f7a39dfb-d5f8-431f-b719-6b20811c1753","isWwObject":true}]},"_wwHover_default":{}},"name":"Children Card","wwObjectBaseId":"b783dc65-d528-4f74-8c14-e27c934c39b1","libraryComponentBaseId":null,"parentSectionId":"42fb6812-db55-4f2e-8698-30ca47a74299"},"fbeff0a3-03b0-4a10-8155-e2ac14045433":{"uid":"fbeff0a3-03b0-4a10-8155-e2ac14045433","_state":{"style":{"mobile":{},"default":{"margin":"0 0 16px 0"},"_wwHover_default":{}},"states":[],"interactions":[]},"content":{"mobile":{},"default":{"tag":"h3","text":{"en":"Not Directed to Children"},"_ww-text_text":{"en":"Not Directed to Children"},"_ww-text_color":"#61378D","_ww-text_fontSize":"24px","_ww-text_fontWeight":"600"},"_wwHover_default":{}},"name":"Children Title","wwObjectBaseId":"d7904e9d-fc9a-4d80-9e32-728e097879ad","libraryComponentBaseId":null,"parentSectionId":"42fb6812-db55-4f2e-8698-30ca47a74299"},"f7a39dfb-d5f8-431f-b719-6b20811c1753":{"uid":"f7a39dfb-d5f8-431f-b719-6b20811c1753","_state":{"style":{"mobile":{},"default":{"margin":"0"},"_wwHover_default":{}},"states":[],"interactions":[]},"content":{"mobile":{},"default":{"tag":"p","text":{"en":"Animal Mitra is not directed to children under 13. We take steps to prevent misuse by minors and remove accounts that violate our policies."},"_ww-text_text":{"en":"Animal Mitra is not directed to children under 13. We take steps to prevent misuse by minors and remove accounts that violate our policies."},"_ww-text_color":"#333333","_ww-text_fontSize":"16px","_ww-text_lineHeight":"1.6"},"_wwHover_default":{}},"name":"Children Description","wwObjectBaseId":"d7904e9d-fc9a-4d80-9e32-728e097879ad","libraryComponentBaseId":null,"parentSectionId":"42fb6812-db55-4f2e-8698-30ca47a74299"},"4fce4b20-79f3-4229-81c8-a4163ebd077e":{"uid":"4fce4b20-79f3-4229-81c8-a4163ebd077e","_state":{"style":{"mobile":{},"default":{"width":"48px","height":"48px","margin":"0 0 16px 0"},"_wwHover_default":{}},"states":[],"interactions":[]},"content":{"mobile":{},"default":{"icon":"lucide/settings","color":"#61378D"},"_wwHover_default":{}},"name":"Design Icon","wwObjectBaseId":"1b1e2173-9b78-42cc-a8ee-a6167caea340","libraryComponentBaseId":null,"parentSectionId":"42fb6812-db55-4f2e-8698-30ca47a74299"},"fe2c7683-b921-4744-8334-5bdb8acd5c8a":{"uid":"fe2c7683-b921-4744-8334-5bdb8acd5c8a","_state":{"style":{"mobile":{},"default":{"margin":"0 0 16px 0"},"_wwHover_default":{}},"states":[],"interactions":[]},"content":{"mobile":{},"default":{"tag":"h3","text":{"en":"Safety by Design"},"_ww-text_text":{"en":"Safety by Design"},"_ww-text_color":"#61378D","_ww-text_fontSize":"24px","_ww-text_fontWeight":"600"},"_wwHover_default":{}},"name":"Design Title","wwObjectBaseId":"d7904e9d-fc9a-4d80-9e32-728e097879ad","libraryComponentBaseId":null,"parentSectionId":"42fb6812-db55-4f2e-8698-30ca47a74299"},"6a1c29df-9127-4ad1-9cc2-2a8cbfc9b1b0":{"uid":"6a1c29df-9127-4ad1-9cc2-2a8cbfc9b1b0","_state":{"style":{"mobile":{},"default":{"border":"1px solid #E5E7EB","display":"block","padding":"32px","boxShadow":"0 4px 6px rgba(0, 0, 0, 0.1)","transition":"all 0.2s ease","borderRadius":"12px","backgroundColor":"#FFFFFF"},"_wwHover_default":{"boxShadow":"0 8px 25px rgba(0, 0, 0, 0.15)"}},"states":[{"id":"_wwHover","label":"hover"}],"interactions":[]},"content":{"mobile":{},"default":{"children":[{"uid":"4fce4b20-79f3-4229-81c8-a4163ebd077e","isWwObject":true},{"uid":"fe2c7683-b921-4744-8334-5bdb8acd5c8a","isWwObject":true},{"uid":"f002e947-09a6-4fea-bb17-3d3bee61e230","isWwObject":true}]},"_wwHover_default":{}},"name":"Design Card","wwObjectBaseId":"b783dc65-d528-4f74-8c14-e27c934c39b1","libraryComponentBaseId":null,"parentSectionId":"42fb6812-db55-4f2e-8698-30ca47a74299"},"f002e947-09a6-4fea-bb17-3d3bee61e230":{"uid":"f002e947-09a6-4fea-bb17-3d3bee61e230","_state":{"style":{"mobile":{},"default":{"margin":"0"},"_wwHover_default":{}},"states":[],"interactions":[]},"content":{"mobile":{},"default":{"tag":"p","text":{"en":"Report/Block features, proactive moderation, keyword filtering, abuse-rate limiting, and rapid escalation for urgent cases."},"_ww-text_text":{"en":"Report/Block features, proactive moderation, keyword filtering, abuse-rate limiting, and rapid escalation for urgent cases."},"_ww-text_color":"#333333","_ww-text_fontSize":"16px","_ww-text_lineHeight":"1.6"},"_wwHover_default":{}},"name":"Design Description","wwObjectBaseId":"d7904e9d-fc9a-4d80-9e32-728e097879ad","libraryComponentBaseId":null,"parentSectionId":"42fb6812-db55-4f2e-8698-30ca47a74299"},"50331479-50ae-419f-a054-42fccec4101a":{"uid":"50331479-50ae-419f-a054-42fccec4101a","_state":{"style":{"mobile":{"display":"grid"},"default":{"display":"grid"}},"states":[],"interactions":[]},"content":{"mobile":{"_ww-grid_columns":["1fr"]},"default":{"children":[{"uid":"23a02d65-9652-41f6-acee-764583a38e85","isWwObject":true},{"uid":"16148ed9-cf79-47b0-bb66-a95c7c715d03","isWwObject":true},{"uid":"6a1c29df-9127-4ad1-9cc2-2a8cbfc9b1b0","isWwObject":true},{"uid":"e5dda1a0-ddf1-463f-ba22-c6de5a6e09be","isWwObject":true}],"_ww-grid_rowGap":"32px","_ww-grid_columns":["1fr","1fr"],"_ww-grid_columnGap":"32px"}},"name":"Commitment Cards","wwObjectBaseId":"b783dc65-d528-4f74-8c14-e27c934c39b1","libraryComponentBaseId":null,"parentSectionId":"42fb6812-db55-4f2e-8698-30ca47a74299"},"8c3ec635-3ea8-4494-907b-9ae06594df83":{"uid":"8c3ec635-3ea8-4494-907b-9ae06594df83","_state":{"style":{"mobile":{},"default":{"width":"48px","height":"48px","margin":"0 0 16px 0"},"_wwHover_default":{}},"states":[],"interactions":[]},"content":{"mobile":{},"default":{"icon":"lucide/gavel","color":"#61378D"},"_wwHover_default":{}},"name":"Compliance Icon","wwObjectBaseId":"1b1e2173-9b78-42cc-a8ee-a6167caea340","libraryComponentBaseId":null,"parentSectionId":"42fb6812-db55-4f2e-8698-30ca47a74299"},"d17dd794-166c-4e1f-9d88-274ea5555933":{"uid":"d17dd794-166c-4e1f-9d88-274ea5555933","_state":{"style":{"mobile":{},"default":{"margin":"0 0 16px 0"},"_wwHover_default":{}},"states":[],"interactions":[]},"content":{"mobile":{},"default":{"tag":"h3","text":{"en":"Legal Compliance"},"_ww-text_text":{"en":"Legal Compliance"},"_ww-text_color":"#61378D","_ww-text_fontSize":"24px","_ww-text_fontWeight":"600"},"_wwHover_default":{}},"name":"Compliance Title","wwObjectBaseId":"d7904e9d-fc9a-4d80-9e32-728e097879ad","libraryComponentBaseId":null,"parentSectionId":"42fb6812-db55-4f2e-8698-30ca47a74299"},"b01f064d-d24d-4256-8779-1760cc42ae04":{"uid":"b01f064d-d24d-4256-8779-1760cc42ae04","_state":{"style":{"mobile":{},"default":{"margin":"0"},"_wwHover_default":{}},"states":[],"interactions":[]},"content":{"mobile":{},"default":{"tag":"p","text":{"en":"We comply with applicable laws and platform policies to protect minors and support lawful investigations."},"_ww-text_text":{"en":"We comply with applicable laws and platform policies to protect minors and support lawful investigations."},"_ww-text_color":"#333333","_ww-text_fontSize":"16px","_ww-text_lineHeight":"1.6"},"_wwHover_default":{}},"name":"Compliance Description","wwObjectBaseId":"d7904e9d-fc9a-4d80-9e32-728e097879ad","libraryComponentBaseId":null,"parentSectionId":"42fb6812-db55-4f2e-8698-30ca47a74299"},"e5dda1a0-ddf1-463f-ba22-c6de5a6e09be":{"uid":"e5dda1a0-ddf1-463f-ba22-c6de5a6e09be","_state":{"style":{"mobile":{},"default":{"border":"1px solid #E5E7EB","display":"block","padding":"32px","boxShadow":"0 4px 6px rgba(0, 0, 0, 0.1)","transition":"all 0.2s ease","borderRadius":"12px","backgroundColor":"#FFFFFF"},"_wwHover_default":{"boxShadow":"0 8px 25px rgba(0, 0, 0, 0.15)"}},"states":[{"id":"_wwHover","label":"hover"}],"interactions":[]},"content":{"mobile":{},"default":{"children":[{"uid":"8c3ec635-3ea8-4494-907b-9ae06594df83","isWwObject":true},{"uid":"d17dd794-166c-4e1f-9d88-274ea5555933","isWwObject":true},{"uid":"b01f064d-d24d-4256-8779-1760cc42ae04","isWwObject":true}]},"_wwHover_default":{}},"name":"Compliance Card","wwObjectBaseId":"b783dc65-d528-4f74-8c14-e27c934c39b1","libraryComponentBaseId":null,"parentSectionId":"42fb6812-db55-4f2e-8698-30ca47a74299"},"ce136b62-3264-4c4c-99c1-9c0acec0ce5a":{"uid":"ce136b62-3264-4c4c-99c1-9c0acec0ce5a","_state":{"style":{"default":{"height":"40px","aspectRatio":"unset"}}},"content":{"default":{"alt":{"en":""},"url":"images/animalfinal_svg-01.svg?_wwcv=39","loading":"lazy","objectFit":null}},"name":"Image","wwObjectBaseId":"3a7d6379-12d3-4387-98ff-b332bb492a63","libraryComponentBaseId":null,"parentSectionId":"97107eea-e44c-4ef1-bd14-a652493f6c8d"},"22fb0397-0677-464c-8a7a-ba7798a6fd7f":{"uid":"22fb0397-0677-464c-8a7a-ba7798a6fd7f","_state":{"style":{"default":{"width":"16px","height":"auto","margin":"0 0 0 8px"},"_wwHover_default":{}},"states":[],"interactions":[]},"content":{"default":{"icon":"lucide/house","color":"#FFFFFF"},"_wwHover_default":{}},"name":"Home Icon","wwObjectBaseId":"1b1e2173-9b78-42cc-a8ee-a6167caea340","libraryComponentBaseId":null,"parentSectionId":"97107eea-e44c-4ef1-bd14-a652493f6c8d"},"3b21d363-8aa1-4268-a3d7-a21f94f23b94":{"uid":"3b21d363-8aa1-4268-a3d7-a21f94f23b94","_state":{"style":{"default":{"width":"24px","height":"auto"}},"states":[],"interactions":[{"id":"987275bb-088f-4b72-bb2a-fde80ed8dbdb","actions":{"1e997b6d-9eab-41b5-b514-d177e8bcc75b":{"id":"1e997b6d-9eab-41b5-b514-d177e8bcc75b","type":"previous-page","pageId":"a87f892b-b1f6-4cd7-a4d6-2989a92963a2"}},"trigger":"click","firstAction":"1e997b6d-9eab-41b5-b514-d177e8bcc75b"}]},"content":{"default":{"icon":"lucide/arrow-left","color":"#61378D"}},"name":"Back Arrow Icon","wwObjectBaseId":"1b1e2173-9b78-42cc-a8ee-a6167caea340","libraryComponentBaseId":null,"parentSectionId":"97107eea-e44c-4ef1-bd14-a652493f6c8d"},"9244b38e-3112-40aa-9b2c-3bace681dc53":{"uid":"9244b38e-3112-40aa-9b2c-3bace681dc53","_state":{"style":{"default":{"cursor":"pointer","display":"flex"}},"states":[],"interactions":[]},"content":{"default":{"children":[{"uid":"3b21d363-8aa1-4268-a3d7-a21f94f23b94","isWwObject":true}],"_ww-layout_rowGap":"8px","_ww-layout_columnGap":"8px","_ww-layout_alignItems":"center","_ww-layout_flexDirection":"row"}},"name":"Back Button","wwObjectBaseId":"b783dc65-d528-4f74-8c14-e27c934c39b1","libraryComponentBaseId":null,"parentSectionId":"97107eea-e44c-4ef1-bd14-a652493f6c8d"},"6d5f33a8-075f-434d-8d4a-4a3a2d2e4d4d":{"uid":"6d5f33a8-075f-434d-8d4a-4a3a2d2e4d4d","_state":{"link":{"type":"internal","pageId":"123e4567-e89b-12d3-a456-426614174000","targetBlank":false},"style":{"default":{"border":"none","cursor":"pointer","display":"flex","padding":"8px 16px","customCss":{"align-items":"center","flex-direction":"row","justify-content":"center"},"transition":"all 0.3s ease","borderRadius":"20px","backgroundColor":"#FF6E06"},"_wwHover_default":{"boxShadow":"0px 4px 8px rgba(255, 110, 6, 0.3)","transform":"translateY(-2px)","backgroundColor":"#E55F00"}},"states":[],"interactions":[{"id":"c0a84613-5ce3-4f4b-abf3-55f701b3c0ca","actions":{"7083f20d-ea49-4fd7-a80a-1ae58279a6e8":{"id":"7083f20d-ea49-4fd7-a80a-1ae58279a6e8","type":"change-page","pageId":"a87f892b-b1f6-4cd7-a4d6-2989a92963a2","navigateMode":"internal"}},"trigger":"click","firstAction":"7083f20d-ea49-4fd7-a80a-1ae58279a6e8"}]},"content":{"default":{"text":{"en":"Home"},"disabled":false,"rightIcon":{"uid":"22fb0397-0677-464c-8a7a-ba7798a6fd7f","isWwObject":true},"buttonType":"button","hasRightIcon":true,"_ww-text_text":{"en":"Home"},"_ww-text_color":"#FFFFFF","_ww-text_fontSize":"14px","_ww-text_fontFamily":"Poppins, sans-serif","_ww-text_fontWeight":"500"},"_wwHover_default":{}},"name":"Home Button","wwObjectBaseId":"59dca300-db78-42e4-a7a6-0cbf22d3cc82","libraryComponentBaseId":null,"parentSectionId":"97107eea-e44c-4ef1-bd14-a652493f6c8d"},"6b58f8b6-4044-4f60-8257-f6982206e753":{"uid":"6b58f8b6-4044-4f60-8257-f6982206e753","_state":{"style":{"default":{"display":"flex"}},"states":[],"interactions":[]},"content":{"default":{"children":[{"uid":"9244b38e-3112-40aa-9b2c-3bace681dc53","isWwObject":true},{"uid":"ce136b62-3264-4c4c-99c1-9c0acec0ce5a","isWwObject":true}],"_ww-layout_rowGap":"12px","_ww-layout_columnGap":"12px","_ww-layout_alignItems":"center","_ww-layout_flexDirection":"row"}},"name":"Back Button Container","wwObjectBaseId":"b783dc65-d528-4f74-8c14-e27c934c39b1","libraryComponentBaseId":null,"parentSectionId":"97107eea-e44c-4ef1-bd14-a652493f6c8d"}},"collections":[],"variables":[],"workflows":[],"formulas":[],"libraryComponents":[]}